igdmapper
