Metadata-Version: 2.1
Name: igdmapper
Version: 0.5.1
Summary: Python script to automate UPnP port mapping
Home-page: https://github.com/jkerdreux-imt/igd-mapper
Author: Jerome Kerdreux
Author-email: Jerome.Kerdreux@imt-atlantique.fr
License: GPL License
Keywords: upnp,igd,nat
Platform: any
Classifier: Programming Language :: Python
Classifier: Topic :: Software Development :: Libraries :: Python Modules
License-File: LICENSE
